[
    {
        "Name": "salt kissed crop rashguard - women's",
        "Price": "$49.73",
        "Savings": "save 28%",
        "Image": "https://www.rei.com/media/d89715b8-5882-478a-8dcb-08b067dc9f11.jpg"
    },
    {
        "Name": "kona rashguard - women's",
        "Price": "$42.73 - $49.73",
        "Savings": "save 30% - 37%",
        "Image": "https://www.rei.com/media/15325960-22b1-4b05-9875-8de5315ec920.jpg"
    },
    {
        "Name": "moonbee long-sleeve lycra rashguard - women's",
        "Price": "$34.93",
        "Savings": "save 30%",
        "Image": "https://www.rei.com/media/d5b87d8b-0fdb-4790-b19e-5bdbc42968fd.jpg"
    },
    {
        "Name": "waterwear rashguard - women's",
        "Price": "$66.73",
        "Savings": "save 25%",
        "Image": "https://www.rei.com/media/511d2b42-69e7-4e8c-a6c4-f6619e1d2486.jpg"
    },
    {
        "Name": "baywatch rashguard - women's",
        "Price": " $39.93",
        "Savings": null,
        "Image": "https://www.rei.com/media/cb4a6734-a4ec-4eaf-9162-46b8c27ab364.jpg"
    },
    {
        "Name": "lake sunshirt - women's",
        "Price": "$46.73",
        "Savings": "save 31%",
        "Image": "https://www.rei.com/media/87d5e4e7-7b3f-4a65-a67d-20d66af413dd.jpg"
    },
    {
        "Name": "dawson rashguard - women's",
        "Price": "$32.73",
        "Savings": "save 37%",
        "Image": "https://www.rei.com/media/8ca13522-8e5d-4a2d-ae02-3840e6450cca.jpg"
    },
    {
        "Name": "baja bound long-sleeve rashguard - women's",
        "Price": "$49.73",
        "Savings": "save 28%",
        "Image": "https://www.rei.com/media/23088167-5ad8-40d2-85ab-bf1d77edd122.jpg"
    },
    {
        "Name": "sunfree long-sleeve quarter-zip top - women's",
        "Price": "$38.73",
        "Savings": "save 29%",
        "Image": "https://www.rei.com/media/4dca6298-5578-41bb-b3bf-f0f0045a79c9.jpg"
    },
    {
        "Name": "stella zip-up jacket - women's",
        "Price": "$74.73",
        "Savings": "save 36%",
        "Image": "https://www.rei.com/media/81dbcc78-e272-4ea2-936a-0f37df2f3ce4.jpg"
    },
    {
        "Name": "sea skippin printed long-sleeve rashguard - women's",
        "Price": " $49.93",
        "Savings": null,
        "Image": "https://www.rei.com/media/72631dfc-7f8a-47f3-849c-754634571bea.jpg"
    },
    {
        "Name": "floral fiesta crop top long-sleeve rashguard - women's",
        "Price": "$32.93",
        "Savings": "save 50%",
        "Image": "https://www.rei.com/media/23995a44-ecb2-4576-a85d-9f0b19d729c6.jpg"
    },
    {
        "Name": "perling crop lycra rashguard - women's",
        "Price": "$34.93",
        "Savings": "save 30%",
        "Image": "https://www.rei.com/media/897e51b5-8b8d-444d-9be1-162ea2d04029.jpg"
    },
    {
        "Name": "swell seeker crop rashguard - women's",
        "Price": "$68.93",
        "Savings": "save 30%",
        "Image": "https://www.rei.com/media/1e819241-9d92-4eb3-9ca4-e327ced7222a.jpg"
    },
    {
        "Name": "dawson rashguard - women's",
        "Price": " $38.93",
        "Savings": null,
        "Image": "https://www.rei.com/media/22464867-44dc-45be-9b4e-c9f915524cc6.jpg"
    }
]